srenamer/__init__.py
srenamer/__main__.py
srenamer/param_types.py
srenamer/renamer.py
srenamer/srenamer.py
srenamer/tmdb_api.py
srenamer-0.3.0.dist-info/entry_points.txt
srenamer-0.3.0.dist-info/LICENSE
srenamer-0.3.0.dist-info/WHEEL
srenamer-0.3.0.dist-info/METADATA
srenamer-0.3.0.dist-info/RECORD
